{
  "basics": {
    "name": "Brandon Nakata",
    "label": "Student",
    "picture": "https://github.com/bhnakata.png",
    "email": "bhnakata@hawaii.edu",
    "phone": "808-861-0687",
    "website": "https://bhnakata.github.io",
    "summary": "I am studying for a B.S. in Computer Engineering at the University of Hawaii. I expect to graduate in Spring, 2025.",
    "location": { "address": "", "postalCode": "96822", "city": "Pearl City", "countryCode": "USA", "region": "Hawaii" },
    "profiles": [
      { "network": "github", "username": "bhnakata", "url": "http://github.com/bhnakata/bhnakata.github.io.git" },
      { "network": "linkedin", "username": "bhnakata", "url": "http://linkedin.com/in/brandon-nakata-8451a0240" },
      { "network": "twitter", "username": "Brandon Nakata", "url": "http://twitter.com/bhnakata" },
      { "network": "instagram", "username": "dbzbt3gt", "url": "http://instagram.com/dbzbt3gt/" }
    ]
  },
  "interests": [
    { "name": "Computer Graphics" },
    { "name": "Coding" },
    { "name": "History" },
    { "name": "Video Games" },
    { "name": "Movies" }
  ],
  "skills": [
    {
      "name": "Languages and Frameworks",
      "keywords": [ "C", "C++", "Kotlin", "Python"]
    },
    {
      "name": "Toolsets/OS",
      "keywords": [ "WindowsOS", "MatLab", "Git/GitHub", "CLion"]
    }
  ],
  "education": [
    {
      "institution": "University of Hawaii, Honolulu, HI",
      "area": "Computer Engineering (expected Spring, 2024)",
      "studyType": "B.S.",
      "startDate": "Fall 2019",
      "endDate": "Present",
      "courses": [
      ]
    }
  ],
  "work": [
    {
      "company": "UH Manoa Board of Publications",
      "position": "Web Developer",
      "website": "",
      "startDate": "2015-08-01",
      "endDate": "Present",
      "summary": "Head of online presence for Ka Leo",
      "highlights": [
        "Maintain, update, and oversee official college newspaper website",
        "Drive, design and build student-community projects for UH Manoa"
      ]
    }
  ],
  
  
  "references": [
    {
      "name": "Available upon request"
    }
  ]
}
